hal9/__init__.py
hal9/cli.py
hal9/code.py
hal9/complete.py
hal9/create.py
hal9/deploy.py
hal9/describe.py
hal9/events.py
hal9/iobind.py
hal9/run.py
hal9/runtimes/chainlit.py
hal9/runtimes/image.py
hal9/runtimes/plumber.py
hal9/runtimes/python.py
hal9/runtimes/r.py
hal9/runtimes/threed.py
hal9/targets/docker.py
hal9/targets/hal9.py
hal9/templates/docker/Dockerfile
hal9/templates/echo/app.py
hal9/templates/groq/app.py
hal9/templates/openai/app.py
hal9/urls.py
hal9-2.8.17.dist-info/METADATA
hal9-2.8.17.dist-info/WHEEL
hal9-2.8.17.dist-info/entry_points.txt
hal9-2.8.17.dist-info/RECORD
