Metadata-Version: 2.3
Name: hal9
Version: 2.8.17
Summary: 
Author: Javier Luraschi
Author-email: javier@hal9.ai
Requires-Python: >=3.8
Classifier: Programming Language :: Python :: 3
Classifier: Programming Language :: Python :: 3.8
Classifier: Programming Language :: Python :: 3.9
Classifier: Programming Language :: Python :: 3.10
Classifier: Programming Language :: Python :: 3.11
Classifier: Programming Language :: Python :: 3.12
Classifier: Programming Language :: Python :: 3.13
Requires-Dist: click (>=8.1.7,<9.0.0)
Requires-Dist: configparser (==7.1.0)
Requires-Dist: requests (>=2.28.2,<3.0.0)
